CHANGES.txt
LICENSE.txt
MANIFEST.in
README.rst
requirements.txt
setup.py
bw2restapi/__init__.py
bw2restapi/activity.py
bw2restapi/database.py
bw2restapi.egg-info/PKG-INFO
bw2restapi.egg-info/SOURCES.txt
bw2restapi.egg-info/dependency_links.txt
bw2restapi.egg-info/entry_points.txt
bw2restapi.egg-info/requires.txt
bw2restapi.egg-info/top_level.txt
bw2restapi/bin/__init__.py
bw2restapi/bin/bw2_restapi.py
bw2restapi/tests/__init__.py
bw2restapi/tests/activity.py
bw2restapi/tests/base.py
bw2restapi/tests/database.py
bw2restapi/tests/fixtures.py