Metadata-Version: 1.1
Name: bw2restapi
Version: 1.2
Summary: UNKNOWN
Home-page: https://bitbucket.org/cmutel/brightway2-restapi
Author: Chris Mutel
Author-email: cmutel@gmail.com
License: Copyright (c) 2014, Chris Mutel and ETH Zürich
